xia_gpt_engine_gitlab/__init__.py
xia_gpt_engine_gitlab/engine.cpython-39-darwin.so
xia_gpt_engine_gitlab/engine_discussion.cpython-39-darwin.so
xia_gpt_engine_gitlab/engine_issue.cpython-39-darwin.so
xia_gpt_engine_gitlab/engine_milestone.cpython-39-darwin.so
xia_gpt_engine_gitlab/engine_notes.cpython-39-darwin.so
xia_gpt_engine_gitlab/engine_wiki.cpython-39-darwin.so
xia_gpt_engine_gitlab-0.0.4.dist-info/LICENSE.txt
xia_gpt_engine_gitlab-0.0.4.dist-info/METADATA
xia_gpt_engine_gitlab-0.0.4.dist-info/WHEEL
xia_gpt_engine_gitlab-0.0.4.dist-info/top_level.txt
xia_gpt_engine_gitlab-0.0.4.dist-info/RECORD
