Metadata-Version: 2.1
Name: xia-gpt-engine-gitlab
Version: 0.0.4
Summary: UNKNOWN
Home-page: https://develop.x-i-a.com/docs/xia-gpt-engine-gitlab/0.0.4/index.html
Author: X-I-A
Author-email: admin@x-i-a.com
License: UNKNOWN
Platform: UNKNOWN
Requires-Python: >=3.9
License-File: LICENSE.txt
Requires-Dist: requests
Requires-Dist: PyYAML
Requires-Dist: xia-engine
Requires-Dist: xia-gpt
Requires-Dist: xia-git-gitlab
